MANIFEST.in
requirements.txt
setup.py
radar/__init__.py
radar/action.py
radar/exceptions.py
radar/interface.py
radar/members.py
radar/query.py
radar/radar.py
radar/record.bak.py
radar/record.py
radar/union.py
radar/utils.py
radar/fields/__init__.py
radar/fields/array.py
radar/fields/boolean.py
radar/fields/field.py
radar/fields/float.py
radar/fields/integer.py
radar/fields/obj.py
radar/fields/string.py
radar_resolver.egg-info/PKG-INFO
radar_resolver.egg-info/SOURCES.txt
radar_resolver.egg-info/dependency_links.txt
radar_resolver.egg-info/requires.txt
radar_resolver.egg-info/top_level.txt