Metadata-Version: 1.0
Name: radar-resolver
Version: 0.2.14
Summary: A python resolver for react-radar Queries and Actions
Home-page: https://github.com/jaredlunde/radar-resolver
Author: Jared Lunde
Author-email: jared.lunde@gmail.com
License: MIT
Platform: UNKNOWN
